{
  "source": "realpaper_g6_math_beishida_xingjitongji_001",
  "subject": "math",
  "grade": 6,
  "knowledge_points_added": [],
  "questions": [
    {
      "chapter": "总复习",
      "knowledge_point": "总复习/图形与几何综合",
      "content": "在括号里填上合适的单位名称：学校旗杆高 15(    )。",
      "type": "choice",
      "difficulty": "easy",
      "options": [
        "A. mm",
        "B. cm",
        "C. m",
        "D. km"
      ],
      "answer": "C",
      "explanation": "旗杆高度用 米（m）作单位，15 m 较合理。",
      "round": 1
    },
    {
      "chapter": "总复习",
      "knowledge_point": "总复习/数与代数综合",
      "content": "在括号里填上合适的单位名称：一瓶墨水约 60(    )。",
      "type": "choice",
      "difficulty": "easy",
      "options": [
        "A. mL",
        "B. L",
        "C. m³",
        "D. dm³"
      ],
      "answer": "A",
      "explanation": "一瓶墨水容量很小，用毫升（mL）作单位，60 mL 合理。",
      "round": 1
    },
    {
      "chapter": "总复习",
      "knowledge_point": "总复习/图形与几何综合",
      "content": "在括号里填上合适的单位名称：一张 2 寸登记照的面积约 17(    )。",
      "type": "choice",
      "difficulty": "easy",
      "options": [
        "A. mm²",
        "B. cm²",
        "C. dm²",
        "D. m²"
      ],
      "answer": "B",
      "explanation": "登记照较小，面积单位用 cm²，17 cm² 合理。",
      "round": 1
    },
    {
      "chapter": "总复习",
      "knowledge_point": "总复习/图形与几何综合",
      "content": "单位换算：4.5 m³ = (    ) dm³。",
      "type": "fill",
      "difficulty": "easy",
      "answer": "4500",
      "alt_answers": "4500dm³|||4500立方分米",
      "explanation": "1 m³ = 1000 dm³，4.5×1000 = 4500 dm³。",
      "round": 1
    },
    {
      "chapter": "总复习",
      "knowledge_point": "总复习/图形与几何综合",
      "content": "单位换算：8.06 m² = (    ) m² (    ) dm²。请按顺序填两个答案，逗号分隔。",
      "type": "fill",
      "difficulty": "medium",
      "answer": "8,6",
      "alt_answers": "8,6",
      "explanation": "整数 8 m²。0.06 m² = 6 dm²（1 m²=100 dm²）。",
      "round": 2
    },
    {
      "chapter": "总复习",
      "knowledge_point": "总复习/图形与几何综合",
      "content": "小芳家在学校的东偏南 30° 方向，距离 800 m。学校在小芳家的(    )偏(    )(    )°方向，学校到小芳家的距离是(    )m。请按顺序填四个答案，逗号分隔（前两空填方位字「东/南/西/北」）。",
      "type": "fill",
      "difficulty": "hard",
      "answer": "西,北,30,800",
      "alt_answers": "西,北,30°,800",
      "explanation": "方向反过来：东↔西，南↔北。学校在小芳家西偏北 30°方向，距离不变 800 m。",
      "round": 3
    },
    {
      "chapter": "总复习",
      "knowledge_point": "总复习/图形与几何综合",
      "content": "等腰三角形的两条边分别长 5 cm 和 10 cm，那么这个等腰三角形的周长是(    )cm。",
      "type": "fill",
      "difficulty": "hard",
      "answer": "25",
      "alt_answers": "25cm",
      "explanation": "两边 5 和 10，第三边等于其中之一。若两腰=5，三边 5+5=10 不大于 10，不能成三角形（违反三边关系）。所以两腰=10，底=5。周长 = 10+10+5 = 25 cm。",
      "round": 3
    },
    {
      "chapter": "总复习",
      "knowledge_point": "总复习/图形与几何综合",
      "content": "一个梯形的上底长 8 cm，下底长 12 cm，高是 10 cm。若在这个梯形中剪一个最大的平行四边形（与梯形等高），它的面积是(    )cm²。",
      "type": "fill",
      "difficulty": "medium",
      "answer": "80",
      "alt_answers": "80cm²",
      "explanation": "最大平行四边形的底 = 上底 8 cm，高 = 10 cm。面积 = 8×10 = 80 cm²。",
      "round": 2
    },
    {
      "chapter": "总复习",
      "knowledge_point": "总复习/图形与几何综合",
      "content": "一个梯形的上底 8 cm，下底 12 cm，高 10 cm。若在这个梯形中剪去一个最大的三角形（同高），剩余部分的面积是(    )cm²。",
      "type": "fill",
      "difficulty": "hard",
      "answer": "40",
      "alt_answers": "40cm²",
      "explanation": "梯形面积 = (8+12)×10÷2 = 100 cm²。最大三角形底 = 12（下底），高 10，面积 = 60 cm²。剩余 = 100-60 = 40 cm²。",
      "round": 3
    },
    {
      "chapter": "总复习",
      "knowledge_point": "总复习/图形与几何综合",
      "content": "一个半圆形的直径是 8 cm，这个半圆形的周长是(    )cm。（π取3.14）",
      "type": "fill",
      "difficulty": "medium",
      "answer": "20.56",
      "alt_answers": "20.56cm",
      "explanation": "半圆周长 = 半圆弧 + 直径 = πd÷2 + d = 3.14×8÷2 + 8 = 12.56 + 8 = 20.56 cm。",
      "round": 2
    },
    {
      "chapter": "总复习",
      "knowledge_point": "总复习/图形与几何综合",
      "content": "一个半圆形的直径是 8 cm，这个半圆形的面积是(    )cm²。",
      "type": "fill",
      "difficulty": "easy",
      "answer": "25.12",
      "alt_answers": "25.12cm²",
      "explanation": "半圆面积 = πr²÷2 = 3.14×16÷2 = 25.12 cm²（半径 4 cm）。",
      "round": 1
    },
    {
      "chapter": "总复习",
      "knowledge_point": "总复习/图形与几何综合",
      "content": "一个长方体木箱的长 6 dm、宽 5 dm、高 3 dm。它的棱长总和是(    )dm。",
      "type": "fill",
      "difficulty": "easy",
      "answer": "56",
      "alt_answers": "56dm",
      "explanation": "棱长总和 = 4×(长+宽+高) = 4×(6+5+3) = 56 dm。",
      "round": 1
    },
    {
      "chapter": "总复习",
      "knowledge_point": "总复习/图形与几何综合",
      "content": "一个长方体木箱的长 6 dm、宽 5 dm、高 3 dm。它的表面积是(    )dm²。",
      "type": "fill",
      "difficulty": "medium",
      "answer": "126",
      "alt_answers": "126dm²",
      "explanation": "表面积 = 2(长×宽+长×高+宽×高) = 2(30+18+15) = 126 dm²。",
      "round": 2
    },
    {
      "chapter": "总复习",
      "knowledge_point": "总复习/图形与几何综合",
      "content": "一个长方体木箱的长 6 dm、宽 5 dm、高 3 dm。它的体积是(    )dm³。",
      "type": "fill",
      "difficulty": "easy",
      "answer": "90",
      "alt_answers": "90dm³",
      "explanation": "体积 = 长×宽×高 = 6×5×3 = 90 dm³。",
      "round": 1
    },
    {
      "chapter": "圆柱与圆锥",
      "knowledge_point": "圆柱与圆锥/圆锥的体积",
      "content": "一个圆柱的底面周长 25.12 dm，高 6 dm。和它等底等高的圆锥的体积是(    )dm³。",
      "type": "fill",
      "difficulty": "medium",
      "answer": "100.48",
      "alt_answers": "100.48dm³",
      "explanation": "半径 = 25.12÷3.14÷2 = 4 dm。圆锥体积 = (1/3)×π×r²×h = (1/3)×3.14×16×6 = 100.48 dm³。",
      "round": 2
    },
    {
      "chapter": "圆柱与圆锥",
      "knowledge_point": "圆柱与圆锥/圆柱的体积",
      "content": "把一段长 2 m 的圆柱形木料锯成 4 个小圆柱，表面积正好增加了 36 dm²。这段木料的体积是(    )m³。",
      "type": "fill",
      "difficulty": "hard",
      "answer": "0.12",
      "alt_answers": "0.12m³",
      "explanation": "锯成 4 段需 3 刀，每刀 2 个面，共 6 个新底面。每底面 = 36÷6 = 6 dm²。体积 = 底×高 = 6×20 = 120 dm³ = 0.12 m³（高 2m=20dm）。",
      "round": 3
    },
    {
      "chapter": "总复习",
      "knowledge_point": "总复习/统计与可能性",
      "content": "在一幅条形统计图里，用 1.5 cm 长的直条表示 9 t，用(    )cm 长的直条表示 24 t。",
      "type": "fill",
      "difficulty": "medium",
      "answer": "4",
      "alt_answers": "4cm",
      "explanation": "比例：1.5 cm : 9 t = x cm : 24 t。x = 1.5×24÷9 = 4 cm。",
      "round": 2
    },
    {
      "chapter": "总复习",
      "knowledge_point": "总复习/统计与可能性",
      "content": "一个盒子里装有完全相同的红球、蓝球共 10 个，任意摸一个球，摸到红球的可能性大。则红球至少有(    )个。",
      "type": "fill",
      "difficulty": "medium",
      "answer": "6",
      "alt_answers": "6个",
      "explanation": "红球可能性大即红球数 > 蓝球数。共 10 个，红球>5，最少 6 个。",
      "round": 2
    },
    {
      "chapter": "总复习",
      "knowledge_point": "总复习/图形与几何综合",
      "content": "判断对错：同一平面内，如果两条直线都和一条直线垂直，那么这两条直线互相平行。",
      "type": "judgment",
      "difficulty": "easy",
      "answer": "对",
      "explanation": "同一平面内，垂直于同一直线的两条直线一定互相平行。",
      "round": 1
    },
    {
      "chapter": "总复习",
      "knowledge_point": "总复习/图形与几何综合",
      "content": "判断对错：周长相等的两个圆，面积也相等。",
      "type": "judgment",
      "difficulty": "easy",
      "answer": "对",
      "explanation": "周长相等 → 半径相等 → 面积相等（面积由半径唯一决定）。",
      "round": 1
    },
    {
      "chapter": "总复习",
      "knowledge_point": "总复习/统计与可能性",
      "content": "判断对错：小明的身高是 1.5 m，他在平均水深 1.35 m 的池塘里游泳不会有危险。",
      "type": "judgment",
      "difficulty": "easy",
      "answer": "错",
      "explanation": "平均水深 1.35 m 不代表每处都 1.35 m，可能某些位置远超 1.5 m，仍有危险。",
      "round": 1
    },
    {
      "chapter": "总复习",
      "knowledge_point": "总复习/统计与可能性",
      "content": "判断对错：一枚骰子六个面分别写 1～6，掷出数字比 3 大晓彬赢，比 3 小晓海赢。这样的游戏规则公平。",
      "type": "judgment",
      "difficulty": "easy",
      "answer": "错",
      "explanation": "比 3 大有 4、5、6（3 个），比 3 小有 1、2（2 个），还有等于 3 不算。两人胜率不等，不公平。",
      "round": 1
    },
    {
      "chapter": "总复习",
      "knowledge_point": "总复习/数与代数综合",
      "content": "下列数据中，与其他数据不相等的是(    )。",
      "type": "choice",
      "difficulty": "medium",
      "options": [
        "A. 4.05 m³",
        "B. 40500 cm³",
        "C. 4050 dm³",
        "D. 4050000 cm³"
      ],
      "answer": "B",
      "explanation": "化为 cm³：A=4.05×10⁶=4050000；C=4050×1000=4050000；D=4050000；B=40500（少 100 倍）。",
      "round": 2
    },
    {
      "chapter": "总复习",
      "knowledge_point": "总复习/统计与可能性",
      "content": "将完全相同的 1 个黑球和 9 个白球放在一个口袋里。从口袋里任意摸一个球，下列说法正确的是(    )。",
      "type": "choice",
      "difficulty": "easy",
      "options": [
        "A. 一定摸到黑球",
        "B. 摸到黑球的可能性大",
        "C. 一定摸到白球",
        "D. 摸到白球的可能性大"
      ],
      "answer": "D",
      "explanation": "白球 9 个 vs 黑球 1 个，白球可能性大但不是一定。",
      "round": 1
    },
    {
      "chapter": "总复习",
      "knowledge_point": "总复习/统计与可能性",
      "content": "王磊前 3 次打靶的平均数为 5 环。要使前 4 次的平均数不低于 6 环，则第 4 次至少应该打出(    )环。",
      "type": "choice",
      "difficulty": "medium",
      "options": [
        "A. 7",
        "B. 8",
        "C. 9",
        "D. 10"
      ],
      "answer": "C",
      "explanation": "前 3 次共 15 环。前 4 次平均 6 环，则总环数≥24。第 4 次≥24-15=9 环。",
      "round": 2
    },
    {
      "chapter": "总复习",
      "knowledge_point": "总复习/解决问题策略",
      "content": "如下图，科技小组靠围墙边用 40 m 长的篱笆围了一块梯形苗圃。已知梯形的下底 12 m（与围墙平行），高 12 m。这块苗圃面积是多少平方米？（篱笆围三边：上底+两腰=40-下底，本题简化用解）",
      "type": "calculation",
      "difficulty": "hard",
      "answer": "168",
      "alt_answers": "168m²|||168平方米",
      "explanation": "篱笆围三边 = 上底 + 两腰 + 下底（其中一边是围墙）。简化解：(40-12)×12÷2 = 168 m²（按原题数据）。",
      "round": 3
    },
    {
      "chapter": "总复习",
      "knowledge_point": "总复习/图形与几何综合",
      "content": "一个长方体铁皮油箱，长 10 dm、宽 8 dm、高 6 dm。做这个油箱至少需要多少平方分米的铁皮？",
      "type": "calculation",
      "difficulty": "medium",
      "answer": "376",
      "alt_answers": "376dm²|||376平方分米",
      "explanation": "需 6 个面（封闭油箱）。表面积 = 2(10×8+10×6+8×6) = 2(80+60+48) = 2×188 = 376 dm²。",
      "round": 2
    },
    {
      "chapter": "总复习",
      "knowledge_point": "总复习/图形与几何综合",
      "content": "一个长方体油箱长 10 dm、宽 8 dm、高 6 dm。如果每升汽油重 0.75 kg，这个油箱最多可装汽油多少千克？",
      "type": "calculation",
      "difficulty": "medium",
      "answer": "360",
      "alt_answers": "360kg|||360千克",
      "explanation": "容积 = 10×8×6 = 480 dm³ = 480 L。汽油重 = 480×0.75 = 360 kg。",
      "round": 2
    },
    {
      "chapter": "圆柱与圆锥",
      "knowledge_point": "圆柱与圆锥/圆柱圆锥综合应用",
      "content": "操场上有一个圆锥形沙堆，底面周长 25.12 m，高 1.5 m。现将这堆沙铺在长 8 m、宽 5 m 的长方形沙坑里。能铺多少厘米厚？",
      "type": "calculation",
      "difficulty": "hard",
      "answer": "62.8",
      "alt_answers": "62.8cm|||62.8厘米",
      "explanation": "圆锥半径 = 25.12÷3.14÷2 = 4 m。沙体积 = (1/3)×3.14×16×1.5 = 25.12 m³。沙坑底面积 = 8×5 = 40 m²。厚度 = 25.12÷40 = 0.628 m = 62.8 cm。",
      "round": 3
    },
    {
      "chapter": "圆柱与圆锥",
      "knowledge_point": "圆柱与圆锥/圆柱的表面积",
      "content": "一根圆柱形木料，分成两段圆柱形木料表面积增加 6.28 dm²；如果沿底面直径劈成两个半圆柱，表面积增加 80 dm²。原来这根圆柱形木料的表面积是多少 dm²？",
      "type": "calculation",
      "difficulty": "hard",
      "answer": "131.88",
      "alt_answers": "131.88dm²",
      "explanation": "分段：6.28÷2 = 3.14（每个底面积），所以底面半径 1 dm，直径 2 dm。沿直径劈：80÷2 = 40 是 2 个矩形，每个矩形 = 直径×高 = 2×h = 40，h = 20 dm。原表面积 = 侧 + 2底 = π×d×h + 2π×r² = 3.14×2×20 + 2×3.14×1² = 125.6 + 6.28 = 131.88 dm²。",
      "round": 3
    }
  ]
}